{
  "run_id": "2026-05-27T14-47-16Z",
  "started_at": "2026-05-27T14:47:16Z",
  "completed_at": "2026-05-27T14:47:16Z",
  "manifest_path": "/Users/tatemccauley/Documents/paramify-fetchers/examples/minimal_run.yaml",
  "invocations": [
    {
      "fetcher_name": "okta_phishing_resistant_mfa",
      "fetcher_version": "0.1.0",
      "target": null,
      "started_at": "2026-05-27T14:47:16Z",
      "completed_at": "2026-05-27T14:47:16Z",
      "duration_sec": 0.267,
      "exit_code": 1,
      "outputs": [
        "okta_phishing_resistant_mfa.json"
      ]
    },
    {
      "fetcher_name": "gitlab_ci_cd_pipeline_config",
      "fetcher_version": "0.1.0",
      "target": {
        "project_id": "group/change-management",
        "url": "https://gitlab.example.com"
      },
      "started_at": "2026-05-27T14:47:16Z",
      "completed_at": "2026-05-27T14:47:16Z",
      "duration_sec": 0.169,
      "exit_code": 1,
      "outputs": [
        "gitlab_ci_cd_pipeline_config_group_change-management.json"
      ]
    },
    {
      "fetcher_name": "gitlab_ci_cd_pipeline_config",
      "fetcher_version": "0.1.0",
      "target": {
        "project_id": "group/terraform",
        "url": "https://gitlab.example.com",
        "branch": "main"
      },
      "started_at": "2026-05-27T14:47:16Z",
      "completed_at": "2026-05-27T14:47:16Z",
      "duration_sec": 0.156,
      "exit_code": 1,
      "outputs": [
        "gitlab_ci_cd_pipeline_config_group_terraform.json"
      ]
    }
  ]
}